{
	"credit": "Made with Blockbench",
	"textures": {
		"0": "custom/niiku1014/yellow5",
		"1": "custom/niiku1014/gray7",
		"particle": "custom/niiku1014/yellow5"
	},
	"elements": [
		{
			"from": [0, 0, 0],
			"to": [1, 16, 1],
			"faces": {
				"north": {"uv": [0, 0, 1, 16], "texture": "#1"},
				"east": {"uv": [0, 0, 1, 16], "texture": "#1"},
				"south": {"uv": [0, 0, 1, 16], "texture": "#1"},
				"west": {"uv": [0, 0, 1, 16], "texture": "#1"},
				"up": {"uv": [0, 0, 1, 1], "texture": "#1"},
				"down": {"uv": [0, 0, 1, 1], "texture": "#1"}
			}
		},
		{
			"from": [15, 0, 0],
			"to": [16, 16, 1],
			"rotation": {"angle": 0, "axis": "y", "origin": [23, 8, 8]},
			"faces": {
				"north": {"uv": [0, 0, 1, 16], "texture": "#1"},
				"east": {"uv": [0, 0, 1, 16], "texture": "#1"},
				"south": {"uv": [0, 0, 1, 16], "texture": "#1"},
				"west": {"uv": [0, 0, 1, 16], "texture": "#1"},
				"up": {"uv": [0, 0, 1, 1], "texture": "#1"},
				"down": {"uv": [0, 0, 1, 1], "texture": "#1"}
			}
		},
		{
			"from": [0, 0, 15],
			"to": [1, 16, 16],
			"rotation": {"angle": 0, "axis": "y", "origin": [-7, 8, 23]},
			"faces": {
				"north": {"uv": [0, 0, 1, 16], "texture": "#1"},
				"east": {"uv": [0, 0, 1, 16], "texture": "#1"},
				"south": {"uv": [0, 0, 1, 16], "texture": "#1"},
				"west": {"uv": [0, 0, 1, 16], "texture": "#1"},
				"up": {"uv": [0, 0, 1, 1], "rotation": 90, "texture": "#1"},
				"down": {"uv": [0, 0, 1, 1], "rotation": 270, "texture": "#1"}
			}
		},
		{
			"from": [15, 0, 15],
			"to": [16, 16, 16],
			"rotation": {"angle": 0, "axis": "y", "origin": [23, 8, 23]},
			"faces": {
				"north": {"uv": [0, 0, 1, 16], "texture": "#1"},
				"east": {"uv": [0, 0, 1, 16], "texture": "#1"},
				"south": {"uv": [0, 0, 1, 16], "texture": "#1"},
				"west": {"uv": [0, 0, 1, 16], "texture": "#1"},
				"up": {"uv": [0, 0, 1, 1], "texture": "#1"},
				"down": {"uv": [0, 0, 1, 1], "texture": "#1"}
			}
		},
		{
			"from": [0, 15, 0],
			"to": [16, 16, 1],
			"rotation": {"angle": 0, "axis": "y", "origin": [23, 8, 8]},
			"faces": {
				"north": {"uv": [0, 0, 16, 1], "texture": "#1"},
				"east": {"uv": [0, 0, 1, 1], "texture": "#1"},
				"south": {"uv": [0, 0, 16, 1], "texture": "#1"},
				"west": {"uv": [0, 0, 1, 1], "texture": "#1"},
				"up": {"uv": [0, 0, 16, 1], "texture": "#1"},
				"down": {"uv": [0, 0, 16, 1], "texture": "#1"}
			}
		},
		{
			"from": [0, -0.1, 0],
			"to": [16, 0.2, 16],
			"rotation": {"angle": 0, "axis": "y", "origin": [23, -7.8, 8]},
			"faces": {
				"north": {"uv": [0, 0, 16, 0.3], "texture": "#1"},
				"east": {"uv": [0, 0, 16, 0.3], "texture": "#1"},
				"south": {"uv": [0, 0, 16, 0.3], "texture": "#1"},
				"west": {"uv": [0, 0, 16, 0.3], "texture": "#1"},
				"up": {"uv": [0, 0, 16, 16], "texture": "#1"},
				"down": {"uv": [0, 0, 16, 16], "texture": "#1"}
			}
		},
		{
			"from": [0.75, 0.2, 0.75],
			"to": [15.25, 15.3, 15.25],
			"rotation": {"angle": 0, "axis": "y", "origin": [23, -7.8, 8]},
			"faces": {
				"north": {"uv": [0, 0, 14.5, 15.1], "texture": "#0"},
				"east": {"uv": [0, 0, 14.5, 15.1], "texture": "#0"},
				"south": {"uv": [0, 0, 14.5, 15.1], "texture": "#0"},
				"west": {"uv": [0, 0, 14.5, 15.1], "texture": "#0"},
				"up": {"uv": [0, 0, 14.5, 14.5], "texture": "#0"},
				"down": {"uv": [0, 0, 14.5, 14.5], "texture": "#0"}
			}
		},
		{
			"from": [0, 15, 0],
			"to": [1, 16, 16],
			"rotation": {"angle": 0, "axis": "y", "origin": [-7, 8, 23]},
			"faces": {
				"north": {"uv": [0, 0, 1, 1], "texture": "#1"},
				"east": {"uv": [0, 0, 16, 1], "texture": "#1"},
				"south": {"uv": [0, 0, 1, 1], "texture": "#1"},
				"west": {"uv": [0, 0, 16, 1], "texture": "#1"},
				"up": {"uv": [0, 0, 16, 1], "rotation": 90, "texture": "#1"},
				"down": {"uv": [0, 0, 16, 1], "rotation": 270, "texture": "#1"}
			}
		},
		{
			"from": [15, 15, 0],
			"to": [16, 16, 16],
			"rotation": {"angle": 0, "axis": "y", "origin": [8, 8, 23]},
			"faces": {
				"north": {"uv": [0, 0, 1, 1], "texture": "#1"},
				"east": {"uv": [0, 0, 16, 1], "texture": "#1"},
				"south": {"uv": [0, 0, 1, 1], "texture": "#1"},
				"west": {"uv": [0, 0, 16, 1], "texture": "#1"},
				"up": {"uv": [0, 0, 16, 1], "rotation": 90, "texture": "#1"},
				"down": {"uv": [0, 0, 16, 1], "rotation": 270, "texture": "#1"}
			}
		},
		{
			"from": [0, 15, 15],
			"to": [16, 16, 16],
			"rotation": {"angle": 0, "axis": "y", "origin": [23, 8, 23]},
			"faces": {
				"north": {"uv": [0, 0, 16, 1], "texture": "#1"},
				"east": {"uv": [0, 0, 1, 1], "texture": "#1"},
				"south": {"uv": [0, 0, 16, 1], "texture": "#1"},
				"west": {"uv": [0, 0, 1, 1], "texture": "#1"},
				"up": {"uv": [0, 0, 16, 1], "texture": "#1"},
				"down": {"uv": [0, 0, 16, 1], "texture": "#1"}
			}
		}
	],
	"display": {
		"thirdperson_righthand": {
			"translation": [0, 4, 0],
			"scale": [0.5, 0.5, 0.5]
		},
		"thirdperson_lefthand": {
			"translation": [0, 4, 0],
			"scale": [0.5, 0.5, 0.5]
		},
		"firstperson_righthand": {
			"scale": [0.5, 0.5, 0.5]
		},
		"firstperson_lefthand": {
			"scale": [0.5, 0.5, 0.5]
		},
		"ground": {
			"scale": [0.3, 0.3, 0.3]
		},
		"gui": {
			"rotation": [21, -31, 0],
			"scale": [0.5, 0.5, 0.5]
		},
		"fixed": {
			"rotation": [-90, 0, 0],
			"translation": [0, 0, -12.2],
			"scale": [1.98, 1.64, 1.99]
		}
	},
	"groups": [
		{
			"name": "group",
			"origin": [8, 8, 8],
			"children": [0, 1, 2, 3, 4, 5, 6, 7, 8, 9]
		}
	]
}